pylenm/__init__.py
pylenm/_imports.py
pylenm/pylenm.py
pylenm/version.py
pylenm-2.7.3.dist-info/licenses/LICENSE
pylenm2/__init__.py
pylenm2/logger_config.py
pylenm2/version.py
pylenm2/data/__init__.py
pylenm2/data/data_module.py
pylenm2/data/fetchers.py
pylenm2/data/filters.py
pylenm2/data/transformation.py
pylenm2/stats/__init__.py
pylenm2/stats/cluster.py
pylenm2/stats/gp.py
pylenm2/stats/metrics.py
pylenm2/stats/preprocess.py
pylenm2/utils/__init__.py
pylenm2/utils/constants.py
pylenm2/utils/custom_exceptions.py
pylenm2/utils/utilities.py
pylenm2/visualization/__init__.py
pylenm2/visualization/correlation.py
pylenm2/visualization/heatmap.py
pylenm2/visualization/map_plot.py
pylenm2/visualization/pca.py
pylenm2/visualization/plots.py
pylenm2/visualization/timeseries.py
pylenm-2.7.3.dist-info/METADATA
pylenm-2.7.3.dist-info/WHEEL
pylenm-2.7.3.dist-info/top_level.txt
pylenm-2.7.3.dist-info/RECORD
