Metadata-Version: 2.4
Name: pylenm
Version: 2.7.3
Summary: This package aims to provide machine learning (ML) functions for performing comprehensive soil and groundwater data analysis, and for supporting the establishment of effective long-term monitoring.
Home-page: https://github.com/hkzhao7/pylenm
Author: Haokai Zhao
Author-email: Haokai Zhao <hkzhao7@mit.edu>
License: MIT
Project-URL: Homepage, https://github.com/hkzhao7/pylenm
Project-URL: Bug Tracker, https://github.com/hkzhao7/pylenm/issues
Project-URL: Documentation, https://pylenm.readthedocs.io/
Project-URL: Source, https://github.com/hkzhao7/pylenm
Classifier: Programming Language :: Python :: 3
Classifier: Operating System :: OS Independent
Requires-Python: >=3.5
Requires-Dist: markdown
Requires-Dist: pandas
Requires-Dist: openpyxl>=2.6.0
Requires-Dist: pyproj>=3.0.1
Requires-Dist: rasterio
Requires-Dist: numpy
Requires-Dist: seaborn
Requires-Dist: matplotlib
Requires-Dist: statsmodels
Requires-Dist: scipy
Requires-Dist: pyproj
Requires-Dist: datetime
Requires-Dist: scikit-learn>=0.24.1
Requires-Dist: supersmoother
Requires-Dist: ipyleaflet>=0.13.0
Requires-Dist: ipywidgets>=7.5.0
Requires-Dist: jupyter
Dynamic: author
Dynamic: home-page
Dynamic: requires-python
